dbchoices/__init__.py
dbchoices/admin.py
dbchoices/apps.py
dbchoices/fields.py
dbchoices/management/__init__.py
dbchoices/management/commands/__init__.py
dbchoices/management/commands/dbchoices.py
dbchoices/migrations/0001_initial.py
dbchoices/migrations/__init__.py
dbchoices/models.py
dbchoices/registry.py
dbchoices/rest_framework/__init__.py
dbchoices/rest_framework/fields.py
dbchoices/signals.py
dbchoices/templatetags/__init__.py
dbchoices/templatetags/dbchoices.py
dbchoices/utils.py
dbchoices/validators.py
django_dbchoices-0.1.1.dist-info/WHEEL
django_dbchoices-0.1.1.dist-info/METADATA
django_dbchoices-0.1.1.dist-info/RECORD
