Metadata-Version: 2.4
Name: django-dbchoices
Version: 0.1.1
Summary: Simple Runtime Choices for Django Models & Forms.
Author: Avishrant Sharma
Author-email: Avishrant Sharma <avishrants@gmail.com>
License-Expression: MIT
Classifier: License :: OSI Approved :: MIT License
Classifier: Framework :: Django
Classifier: Framework :: Django :: 3
Classifier: Framework :: Django :: 4
Classifier: Framework :: Django :: 5
Classifier: Framework :: Django :: 6
Classifier: Programming Language :: Python :: 3
Classifier: Programming Language :: Python :: 3.10
Classifier: Programming Language :: Python :: 3.11
Classifier: Programming Language :: Python :: 3.12
Classifier: Programming Language :: Python :: 3.13
Requires-Dist: django
Requires-Python: >=3.10
Project-URL: Homepage, https://github.com/AvishrantsSh/django-dbchoices
Project-URL: Issues, https://github.com/AvishrantsSh/django-dbchoices/issues
Project-URL: Repository, https://github.com/AvishrantsSh/django-dbchoices.git
